cygnods/__init__.py
cygnods/annotators.py
LICENSE
cygnods-0.1.3.dist-info/LICENSE
cygnods-0.1.3.dist-info/WHEEL
cygnods-0.1.3.dist-info/METADATA
cygnods-0.1.3.dist-info/RECORD
