Metadata-Version: 2.1
Name: cygnods
Version: 0.1.3
Summary: Small library to handle most frequent CYGNO dataset operations with python
Home-page: https://github.com/CYGNO-ML/cygnods
License: GPL
Keywords: Dark Matter,Machine Learning,Multimodal
Author: Gustavo Viera López
Author-email: gvieralopez@gmail.com
Requires-Python: >=3.8,<4.0
Classifier: License :: Other/Proprietary License
Classifier: Programming Language :: Python :: 3
Classifier: Programming Language :: Python :: 3.10
Classifier: Programming Language :: Python :: 3.8
Classifier: Programming Language :: Python :: 3.9
Requires-Dist: configparser (>=5.2.0)
Requires-Dist: numpy (>=1.16.5)
Requires-Dist: opencv-python (>=4.4.0)
Project-URL: Repository, https://github.com/CYGNO-ML/cygnods
